feedmob_mcp_adjust/__init__.py
feedmob_mcp_adjust/internal_api_service.py
feedmob_mcp_adjust/server.py
feedmob_mcp_adjust-1.0.0.dist-info/METADATA
feedmob_mcp_adjust-1.0.0.dist-info/WHEEL
feedmob_mcp_adjust-1.0.0.dist-info/entry_points.txt
feedmob_mcp_adjust-1.0.0.dist-info/RECORD
