Metadata-Version: 2.4
Name: feedmob-mcp-adjust
Version: 1.0.0
Summary: Feedmob MCP Server of Adjust - MMP MCP Server
Requires-Python: >=3.12.0
Requires-Dist: httpx[socks]>=0.27.2
Requires-Dist: mcp>=1.3.0
